mark/__main__.py
mark/cli.py
mark/config.py
mark/llm.py
mark/llm_request.py
mark/llm_response.py
mark/markdown_file.py
mark/scraper.py
mark/setup_browsers.py
mark/templates/default_system_prompt.md
mark-0.11.0.dist-info/METADATA
mark-0.11.0.dist-info/WHEEL
mark-0.11.0.dist-info/entry_points.txt
mark-0.11.0.dist-info/licenses/LICENSE
mark-0.11.0.dist-info/RECORD
