Metadata-Version: 2.4
Name: mark
Version: 0.11.0
Summary: Mark lets you seamlessly use markdown, images and links to interact with LLMs
License-Expression: MIT
License-File: LICENSE
Author: Ryan Elston
Author-email: elston.ryan@gmail.com
Requires-Python: >=3.10
Classifier: Programming Language :: Python :: 3
Classifier: Operating System :: OS Independent
Requires-Dist: PyYAML (==6.0.2)
Requires-Dist: click (>=8.1.8,<9.0.0)
Requires-Dist: click-default-group (>=1.2.4,<2.0.0)
Requires-Dist: crawl4ai (>=0.7.8,<0.8.0)
Requires-Dist: ipython (==8.32.0)
Requires-Dist: llm (>=0.25,<0.26)
Project-URL: Homepage, https://github.com/relston/mark
Project-URL: Issues, https://github.com/relston/mark/issues
